odoo/addons/sale_cancel_confirmed_invoice/README.rst
odoo/addons/sale_cancel_confirmed_invoice/__init__.py
odoo/addons/sale_cancel_confirmed_invoice/__manifest__.py
odoo/addons/sale_cancel_confirmed_invoice/i18n/sale_cancel_confirmed_invoice.pot
odoo/addons/sale_cancel_confirmed_invoice/models/__init__.py
odoo/addons/sale_cancel_confirmed_invoice/models/res_company.py
odoo/addons/sale_cancel_confirmed_invoice/models/res_config_settings.py
odoo/addons/sale_cancel_confirmed_invoice/models/sale_order.py
odoo/addons/sale_cancel_confirmed_invoice/readme/CONTRIBUTORS.rst
odoo/addons/sale_cancel_confirmed_invoice/readme/DESCRIPTION.rst
odoo/addons/sale_cancel_confirmed_invoice/readme/USAGE.rst
odoo/addons/sale_cancel_confirmed_invoice/static/description/icon.png
odoo/addons/sale_cancel_confirmed_invoice/static/description/index.html
odoo/addons/sale_cancel_confirmed_invoice/tests/__init__.py
odoo/addons/sale_cancel_confirmed_invoice/tests/test_sale_cancel_confirmed_invoice.py
odoo/addons/sale_cancel_confirmed_invoice/views/res_config_settings_views.xml
odoo/addons/sale_cancel_confirmed_invoice/wizards/__init__.py
odoo/addons/sale_cancel_confirmed_invoice/wizards/sale_order_cancel.py
odoo/addons/sale_cancel_confirmed_invoice/wizards/sale_order_cancel_view.xml
odoo_addon_sale_cancel_confirmed_invoice-15.0.1.0.0.1.dist-info/METADATA
odoo_addon_sale_cancel_confirmed_invoice-15.0.1.0.0.1.dist-info/WHEEL
odoo_addon_sale_cancel_confirmed_invoice-15.0.1.0.0.1.dist-info/top_level.txt
odoo_addon_sale_cancel_confirmed_invoice-15.0.1.0.0.1.dist-info/RECORD
